{
  "TOOL_BUG_ID": "Nopol-Closure-31",
  "SLB": {
    "median": 62.3,
    "std": 0.44475782602392105,
    "max": 63.0,
    "min": 61.3
  },
  "PowerAvg": {
    "median": 111.8,
    "std": 5.191228866353048,
    "max": 112.8,
    "min": 91.8
  },
  "Time": {
    "median": 329.9928150177002,
    "std": 210.455648745248,
    "max": 1148.0950989723206,
    "min": 326.41256380081177
  },
  "Joules": {
    "median": 39544.81923409701,
    "std": 18114.637410176078,
    "max": 109948.2675159335,
    "min": 38882.82334302664
  },
  "JoulesNormalized": {
    "median": 18999.91638413667,
    "std": 4949.701081064723,
    "max": 38192.32383016347,
    "min": 18775.360731160636
  },
  "NrPatches": {
    "median": 2,
    "std": 0.0,
    "max": 2,
    "min": 2
  },
  "Joules_Per_PatchMedian": [
    1592.1958750367164,
    4818.305329883098
  ],
  "ExecutionTime_Per_PatchMedian": [
    11.999946117401123,
    39.01961708068848
  ],
  "JoulesNormalized_Per_PatchMedian": [
    846.9689925312995,
    2373.829623401165
  ],
  "Correctness_Per_Patch": [
    "I",
    "I"
  ]
}