{
  "Group_ID": "s_200_299",
  "TOOL_BUG_ID": "Avatar-Math-32",
  "ExecutionsIds": [
    "200"
  ],
  "NrExecutions": 1,
  "NrOutliers": 0,
  "SLB": {
    "median": 62.7,
    "std": 0,
    "max": 62.7,
    "min": 62.7
  },
  "PowerAvg": {
    "median": 94.4,
    "std": 0,
    "max": 94.4,
    "min": 94.4
  },
  "Time": {
    "median": 339.19268703460693,
    "std": 0,
    "max": 339.19268703460693,
    "min": 339.19268703460693
  },
  "Joules": {
    "median": 31862.69341926575,
    "std": 0,
    "max": 31862.69341926575,
    "min": 31862.69341926575
  },
  "JoulesNormalized": {
    "median": 10595.311942195895,
    "std": 0,
    "max": 10595.311942195895,
    "min": 10595.311942195895
  },
  "NrPatches": {
    "median": 0,
    "std": 0,
    "max": 0,
    "min": 0
  },
  "Joules_Per_PatchMedian": [],
  "ExecutionTime_Per_PatchMedian": [],
  "JoulesNormalized_Per_PatchMedian": [],
  "Correctness_Per_Patch": []
}