{
  "Group_ID": "s_200_299",
  "TOOL_BUG_ID": "Nopol-Closure-119",
  "ExecutionsIds": [
    "200",
    "210",
    "250",
    "251"
  ],
  "NrExecutions": 4,
  "NrOutliers": 1,
  "SLB": {
    "median": 63.849999999999994,
    "std": 0.3872983346207383,
    "max": 64.1,
    "min": 63.2
  },
  "PowerAvg": {
    "median": 119.94999999999999,
    "std": 0.5909032633745298,
    "max": 120.5,
    "min": 119.1
  },
  "Time": {
    "median": 17947.50763106346,
    "std": 7.30977358402593,
    "max": 17948.513252019882,
    "min": 17933.29263305664
  },
  "Joules": {
    "median": 2212239.1840457963,
    "std": 7666.0676965318735,
    "max": 2218688.0081146234,
    "min": 2201117.568461668
  },
  "JoulesNormalized": {
    "median": 1066190.1612964985,
    "std": 4733.044744301577,
    "max": 1073678.4381721013,
    "min": 1062458.0496755347
  },
  "NrPatches": {
    "median": 0.0,
    "std": 0.0,
    "max": 0,
    "min": 0
  },
  "Joules_Per_PatchMedian": [],
  "ExecutionTime_Per_PatchMedian": [],
  "JoulesNormalized_Per_PatchMedian": [],
  "Correctness_Per_Patch": []
}