{
  "Group_ID": "s_200_299",
  "TOOL_BUG_ID": "Prapr-Closure-124",
  "ExecutionsIds": [
    "250",
    "251",
    "252",
    "253",
    "254"
  ],
  "NrExecutions": 5,
  "NrOutliers": 0,
  "SLB": {
    "median": 62.6,
    "std": 0.1923538406167136,
    "max": 62.9,
    "min": 62.4
  },
  "PowerAvg": {
    "median": 62.8,
    "std": 0.19235384061671304,
    "max": 63.1,
    "min": 62.6
  },
  "Time": {
    "median": 63.798645973205566,
    "std": 0.39809512908377126,
    "max": 64.33898901939392,
    "min": 63.39932703971863
  },
  "Joules": {
    "median": 4244.503290379048,
    "std": 103.58559779796755,
    "max": 4460.325221586228,
    "min": 4213.207835388183
  },
  "JoulesNormalized": {
    "median": 252.9443905949597,
    "std": 85.13511126746327,
    "max": 432.70450897216824,
    "min": 229.38334656953884
  },
  "NrPatches": {
    "median": 0,
    "std": 0.0,
    "max": 0,
    "min": 0
  },
  "Joules_Per_PatchMedian": [],
  "ExecutionTime_Per_PatchMedian": [],
  "JoulesNormalized_Per_PatchMedian": [],
  "Correctness_Per_Patch": []
}