{
  "TOOL_BUG_ID": "dynamoth-Closure-55",
  "SLB": {
    "median": 64.0,
    "std": 0.6426507605223853,
    "max": 64.2,
    "min": 62.8
  },
  "PowerAvg": {
    "median": 150.4,
    "std": 1.8676188047886084,
    "max": 150.4,
    "min": 146.2
  },
  "Time": {
    "median": 11291.245620012283,
    "std": 6588.999564949967,
    "max": 18039.839709997177,
    "min": 3074.552505016327
  },
  "Joules": {
    "median": 1744224.5921664955,
    "std": 948418.8486800231,
    "max": 2630906.990827168,
    "min": 455738.6453027964
  },
  "JoulesNormalized": {
    "median": 1020455.7479237082,
    "std": 529238.7834264066,
    "max": 1492593.105126346,
    "min": 262656.74798777106
  },
  "NrPatches": {
    "median": 0,
    "std": 0.0,
    "max": 0,
    "min": 0
  },
  "Joules_Per_PatchMedian": [],
  "ExecutionTime_Per_PatchMedian": [],
  "JoulesNormalized_Per_PatchMedian": [],
  "Correctness_Per_Patch": []
}