{
  "VARIANT_ID": "14420",
  "VALIDATION": "|true|0|2954|[]|",
  "patchhunks": [
    {
      "LOCATION": "org.apache.commons.math.linear.OpenMapRealVector",
      "PATH": "\\/home\\/user\\/speedy_runner\\/scripts\\/workingdir\\/jGenProg\\/Math_49\\/src\\/main\\/java\\/org\\/apache\\/commons\\/math\\/linear\\/OpenMapRealVector.java",
      "INGREDIENT_SCOPE": "LOCAL",
      "SUSPICIOUNESS": "0.577",
      "INGREDIENT_PARENT": "entries.put(index, value)",
      "PATCH_HUNK_TYPE": "CtInvocationImpl|CtBlockImpl",
      "ORIGINAL_CODE": "entries.remove(index)",
      "BUGGY_CODE_TYPE": "CtInvocationImpl|CtBlockImpl",
      "OPERATOR": "ReplaceOp",
      "MODIFIED_FILE_PATH": "\\/home\\/user\\/speedy_runner\\/scripts\\/workingdir\\/jGenProg\\/Math_49\\/.\\/output_astor\\/AstorMain-Math49\\/\\/src\\/\\/variant-14420\\/org\\/apache\\/commons\\/math\\/linear\\/OpenMapRealVector.java",
      "LINE": "667",
      "MP_RANKING": "12",
      "PATCH_HUNK_CODE": "entries.put(index, value)"
    }
  ],
  "TIME": "11388",
  "GENERATION": "7210",
  "FOLDER_SOLUTION_CODE": "\\/home\\/user\\/speedy_runner\\/scripts\\/workingdir\\/jGenProg\\/Math_49\\/.\\/output_astor\\/AstorMain-Math49\\/\\/src\\/\\/variant-14420",
  "PATCH_DIFF_ORIG": "--- \\/home\\/user\\/speedy_runner\\/scripts\\/workingdir\\/jGenProg\\/Math_49\\/src\\/main\\/java\\/org\\/apache\\/commons\\/math\\/linear\\/OpenMapRealVectorjava\\n+++ \\/home\\/user\\/speedy_runner\\/scripts\\/workingdir\\/jGenProg\\/Math_49\\/src\\/main\\/java\\/org\\/apache\\/commons\\/math\\/linear\\/OpenMapRealVectorjava\\n@@ -666,2 +666,2 @@\\n-\\t\\t} else if (entries.containsKey(index)) {\\n-\\t\\t\\tentries.remove(index);\\n+\\t\\t} else if (entries.containsKey(index)) { \\t\\t\\tentries.put(index, value);\\n+\\n\\n"
}